README.rst
setup.py
cfncluster_node.egg-info/PKG-INFO
cfncluster_node.egg-info/SOURCES.txt
cfncluster_node.egg-info/dependency_links.txt
cfncluster_node.egg-info/entry_points.txt
cfncluster_node.egg-info/not-zip-safe
cfncluster_node.egg-info/requires.txt
cfncluster_node.egg-info/top_level.txt
jobwatcher/__init__.py
jobwatcher/jobwatcher.py
jobwatcher/plugins/__init__.py
jobwatcher/plugins/sge.py
jobwatcher/plugins/slurm.py
jobwatcher/plugins/test.py
jobwatcher/plugins/torque.py
jobwatcher/plugins/unittests.py
jobwatcher/plugins/utils.py
nodewatcher/__init__.py
nodewatcher/nodewatcher.py
nodewatcher/plugins/__init__.py
nodewatcher/plugins/openlava.py
nodewatcher/plugins/sge.py
nodewatcher/plugins/slurm.py
nodewatcher/plugins/test.py
nodewatcher/plugins/torque.py
sqswatcher/__init__.py
sqswatcher/sqswatcher.py
sqswatcher/plugins/__init__.py
sqswatcher/plugins/openlava.py
sqswatcher/plugins/sge.py
sqswatcher/plugins/slurm.py
sqswatcher/plugins/test.py
sqswatcher/plugins/torque.py