Metadata-Version: 1.1
Name: cfncluster-node
Version: 1.6.0
Summary: cfncluster-node provides the scripts for a cfncluster node.
Home-page: https://github.com/awslabs/cfncluster
Author: Dougal Ballantyne
Author-email: dougalb@amazon.com
License: Apache License 2.0
Platform: UNKNOWN
Classifier: Development Status :: 5 - Production/Stable
Classifier: Environment :: Console
Classifier: Programming Language :: Python
Classifier: Topic :: Scientific/Engineering
Classifier: License :: OSI Approved :: Apache Software License
